{
  "projectRoot": "/home/max/Github/nunua-polepoe",
  "batchFiles": [
    {"path": "src/App.tsx", "language": "typescript", "sizeLines": 209, "fileCategory": "code"},
    {"path": "src/components/AppSidebar.tsx", "language": "typescript", "sizeLines": 304, "fileCategory": "code"},
    {"path": "src/components/Layout.tsx", "language": "typescript", "sizeLines": 133, "fileCategory": "code"},
    {"path": "src/components/SuperAdminLayout.tsx", "language": "typescript", "sizeLines": 101, "fileCategory": "code"},
    {"path": "src/components/SuperAdminSidebar.tsx", "language": "typescript", "sizeLines": 112, "fileCategory": "code"},
    {"path": "src/components/WhatsAppButton.tsx", "language": "typescript", "sizeLines": 119, "fileCategory": "code"},
    {"path": "src/components/ui/collapsible.tsx", "language": "typescript", "sizeLines": 9, "fileCategory": "code"},
    {"path": "src/components/ui/separator.tsx", "language": "typescript", "sizeLines": 20, "fileCategory": "code"},
    {"path": "src/components/ui/sheet.tsx", "language": "typescript", "sizeLines": 107, "fileCategory": "code"},
    {"path": "src/components/ui/sidebar.tsx", "language": "typescript", "sizeLines": 637, "fileCategory": "code"},
    {"path": "src/components/ui/skeleton.tsx", "language": "typescript", "sizeLines": 7, "fileCategory": "code"},
    {"path": "src/components/ui/sonner.tsx", "language": "typescript", "sizeLines": 27, "fileCategory": "code"},
    {"path": "src/components/ui/tooltip.tsx", "language": "typescript", "sizeLines": 28, "fileCategory": "code"},
    {"path": "src/hooks/use-mobile.tsx", "language": "typescript", "sizeLines": 19, "fileCategory": "code"},
    {"path": "src/hooks/useAuth.tsx", "language": "typescript", "sizeLines": 35, "fileCategory": "code"},
    {"path": "src/hooks/useUserRole.ts", "language": "typescript", "sizeLines": 76, "fileCategory": "code"},
    {"path": "src/pages/Dashboard.tsx", "language": "typescript", "sizeLines": 553, "fileCategory": "code"},
    {"path": "src/pages/Landing.tsx", "language": "typescript", "sizeLines": 570, "fileCategory": "code"},
    {"path": "src/pages/NotFound.tsx", "language": "typescript", "sizeLines": 78, "fileCategory": "code"},
    {"path": "src/pages/SuperAdmin.tsx", "language": "typescript", "sizeLines": 187, "fileCategory": "code"}
  ],
  "batchImportData": {
    "src/App.tsx": ["src/components/Layout.tsx","src/components/providers/SubscriptionProvider.tsx","src/components/SubscriptionGuard.tsx","src/components/SuperAdminLayout.tsx","src/components/ui/sonner.tsx","src/components/ui/toaster.tsx","src/components/ui/tooltip.tsx","src/components/WhatsAppButton.tsx","src/hooks/useAuth.tsx","src/hooks/useUserRole.ts","src/pages/Auth.tsx","src/pages/ClientDashboard.tsx","src/pages/Clients.tsx","src/pages/Dashboard.tsx","src/pages/Invoices.tsx","src/pages/Landing.tsx","src/pages/NotFound.tsx","src/pages/Payments.tsx","src/pages/Products.tsx","src/pages/Settings.tsx","src/pages/Subscription.tsx","src/pages/SuperAdmin.tsx","src/pages/SuperAdminTenants.tsx","src/pages/SuperAdminUsers.tsx"],
    "src/components/AppSidebar.tsx": ["src/components/clients/ClientDialog.tsx","src/components/FeatureGate.tsx","src/components/ui/collapsible.tsx","src/components/ui/sidebar.tsx","src/hooks/use-mobile.tsx","src/hooks/useUserRole.ts","src/lib/featureFlags.ts","src/lib/utils.ts"],
    "src/components/Layout.tsx": ["src/components/AppSidebar.tsx","src/components/GlobalSearch.tsx","src/components/NotificationDropdown.tsx","src/components/TrialBanner.tsx","src/components/ui/button.tsx","src/components/ui/dropdown-menu.tsx","src/components/ui/input.tsx","src/components/ui/sidebar.tsx","src/hooks/useAuth.tsx","src/hooks/useUserRole.ts","src/integrations/supabase/client.ts"],
    "src/components/SuperAdminLayout.tsx": ["src/components/SuperAdminSidebar.tsx","src/components/ui/button.tsx","src/components/ui/dropdown-menu.tsx","src/components/ui/sidebar.tsx","src/hooks/useAuth.tsx"],
    "src/components/SuperAdminSidebar.tsx": ["src/components/ui/sidebar.tsx","src/hooks/use-mobile.tsx","src/lib/utils.ts"],
    "src/components/WhatsAppButton.tsx": ["src/components/ui/dialog.tsx"],
    "src/components/ui/collapsible.tsx": [],
    "src/components/ui/separator.tsx": ["src/lib/utils.ts"],
    "src/components/ui/sheet.tsx": ["src/lib/utils.ts"],
    "src/components/ui/sidebar.tsx": ["src/components/ui/button.tsx","src/components/ui/input.tsx","src/components/ui/separator.tsx","src/components/ui/sheet.tsx","src/components/ui/skeleton.tsx","src/components/ui/tooltip.tsx","src/hooks/use-mobile.tsx","src/lib/utils.ts"],
    "src/components/ui/skeleton.tsx": ["src/lib/utils.ts"],
    "src/components/ui/sonner.tsx": [],
    "src/components/ui/tooltip.tsx": ["src/lib/utils.ts"],
    "src/hooks/use-mobile.tsx": [],
    "src/hooks/useAuth.tsx": ["src/integrations/supabase/client.ts"],
    "src/hooks/useUserRole.ts": ["src/hooks/useAuth.tsx","src/integrations/supabase/client.ts"],
    "src/pages/Dashboard.tsx": ["src/api/clients.api.ts","src/api/invoices.api.ts","src/api/payments.api.ts","src/api/products.api.ts","src/components/FeatureGate.tsx","src/components/ui/button.tsx","src/components/ui/card.tsx","src/components/ui/chart.tsx","src/components/ui/dialog.tsx","src/integrations/supabase/client.ts"],
    "src/pages/Landing.tsx": ["src/components/ui/button.tsx","src/hooks/useAuth.tsx"],
    "src/pages/NotFound.tsx": [],
    "src/pages/SuperAdmin.tsx": ["src/api/clients.api.ts","src/api/invoices.api.ts","src/api/payments.api.ts","src/integrations/supabase/client.ts"]
  }
}
